.cvsignore
.project
README
ez_setup.py
setup.cfg
setup.py
setup.sh
examples/.cvsignore
examples/README
examples/setup.sh
examples/config/connection.xml
examples/config/example_graphs.xml
examples/config/example_queries.xml
examples/config/matplotlibrc
examples/config/prod.conf
examples/config/website.xml
examples/tools/graphtool-create-exampledb.py
examples/tools/graphtool-example.py
graphtool.egg-info/PKG-INFO
graphtool.egg-info/SOURCES.txt
graphtool.egg-info/dependency_links.txt
graphtool.egg-info/requires.txt
graphtool.egg-info/top_level.txt
src/graphtool/__init__.py
src/graphtool/base/__init__.py
src/graphtool/base/iterator.py
src/graphtool/base/xml_config.py
src/graphtool/database/__init__.py
src/graphtool/database/connection_manager.py
src/graphtool/database/queries.py
src/graphtool/database/query_handler.py
src/graphtool/database/result_aggregator.py
src/graphtool/graphs/__init__.py
src/graphtool/graphs/basic.py
src/graphtool/graphs/common.py
src/graphtool/graphs/common_graphs.py
src/graphtool/graphs/graph.py
src/graphtool/tools/__init__.py
src/graphtool/tools/cache.py
src/graphtool/tools/common.py
src/graphtool/tools/keepalive.py
src/graphtool/tools/query_output.py
src/graphtool/tools/treemap.py
src/graphtool/web/__init__.py
src/graphtool/web/bonsai.py
src/graphtool/web/security.py
static_content/.cvsignore
static_content/CMSbwl3.png
static_content/__init__.py
static_content/calbtn.gif
static_content/style.css
static_content/web_layout.xsl
static_content/web_viewer.xsl
static_content/wz_tooltip.js
static_content/wz_tooltip_4.js
static_content/xml_results.xsl
