Metadata-Version: 1.0
Name: graphtool
Version: 0.5.2
Summary: CMS Common Graphing Package.
Home-page: UNKNOWN
Author: Brian Bockelman
Author-email: bbockelm@math.unl.edu
License: UNKNOWN
Platform: UNKNOWN
Classifier: Development Status :: 2 - Pre-Alpha
Classifier: Intended Audience :: Developers
Classifier: Programming Language :: Python
Classifier: Natural Language :: English
Classifier: Operating System :: POSIX
